[
  {
    "op": "core/column-removal",
    "columnName": "fecha",
    "description": "Eliminar columna fecha"
  },
  {
    "op": "core/fill-down",
    "engineConfig": {
      "facets": [
        {
          "type": "list",
          "name": "fleet",
          "expression": "value",
          "columnName": "fleet",
          "invert": false,
          "omitBlank": false,
          "omitError": false,
          "selection": [],
          "selectBlank": true,
          "selectError": false
        }
      ],
      "mode": "row-based"
    },
    "columnName": "idBike",
    "description": "Rellenar las celdas en la columna idBike"
  },
  {
    "op": "core/blank-down",
    "engineConfig": {
      "facets": [],
      "mode": "row-based"
    },
    "columnName": "idBike",
    "description": "Vaciar las celdas en la columna idBike"
  },
  {
    "op": "core/row-removal",
    "engineConfig": {
      "facets": [
        {
          "type": "list",
          "name": "fleet",
          "expression": "value",
          "columnName": "fleet",
          "invert": false,
          "omitBlank": false,
          "omitError": false,
          "selection": [],
          "selectBlank": true,
          "selectError": false
        }
      ],
      "mode": "row-based"
    },
    "description": "Remove rows"
  },
  {
    "op": "core/column-removal",
    "columnName": "fleet",
    "description": "Eliminar columna fleet"
  },
  {
    "op": "core/column-addition",
    "engineConfig": {
      "facets": [],
      "mode": "row-based"
    },
    "baseColumnName": "geolocation_unlock",
    "expression": "jython:value = value.split(\",\")\nreturn value[1].split(\"[\")[1]",
    "onError": "set-to-blank",
    "newColumnName": "Unlock_Coor_x",
    "columnInsertIndex": 3,
    "description": "Crear la columna Unlock_Coor_x en el índice 3 basada en la columna geolocation_unlock usando la expresión jython:value = value.split(\",\")\nreturn value[1].split(\"[\")[1]"
  },
  {
    "op": "core/column-addition",
    "engineConfig": {
      "facets": [],
      "mode": "row-based"
    },
    "baseColumnName": "geolocation_unlock",
    "expression": "jython:value = value.split(\",\")\nreturn value[2].split(\"]\")[0]",
    "onError": "set-to-blank",
    "newColumnName": "Unlock_Coor_y",
    "columnInsertIndex": 3,
    "description": "Crear la columna Unlock_Coor_y en el índice 3 basada en la columna geolocation_unlock usando la expresión jython:value = value.split(\",\")\nreturn value[2].split(\"]\")[0]"
  },
  {
    "op": "core/column-removal",
    "columnName": "geolocation_unlock",
    "description": "Eliminar columna geolocation_unlock"
  },
  {
    "op": "core/column-addition",
    "engineConfig": {
      "facets": [],
      "mode": "row-based"
    },
    "baseColumnName": "geolocation_lock",
    "expression": "jython:value = value.split(\",\")\nreturn value[1].split(\"[\")[1]",
    "onError": "set-to-blank",
    "newColumnName": "Lock_Coord_x",
    "columnInsertIndex": 9,
    "description": "Crear la columna Lock_Coord_x en el índice 9 basada en la columna geolocation_lock usando la expresión jython:value = value.split(\",\")\nreturn value[1].split(\"[\")[1]"
  },
  {
    "op": "core/column-addition",
    "engineConfig": {
      "facets": [],
      "mode": "row-based"
    },
    "baseColumnName": "geolocation_lock",
    "expression": "jython:value = value.split(\",\")\nreturn value[2].split(\"]\")[0]",
    "onError": "set-to-blank",
    "newColumnName": "Lock_Coord_y",
    "columnInsertIndex": 9,
    "description": "Crear la columna Lock_Coord_y en el índice 9 basada en la columna geolocation_lock usando la expresión jython:value = value.split(\",\")\nreturn value[2].split(\"]\")[0]"
  },
  {
    "op": "core/column-removal",
    "columnName": "geolocation_lock",
    "description": "Eliminar columna geolocation_lock"
  },
  {
    "op": "core/column-rename",
    "oldColumnName": "Unlock_Coor_y",
    "newColumnName": "Unlock_Coord_y",
    "description": "Renombra la columna Unlock_Coor_y a Unlock_Coord_y"
  },
  {
    "op": "core/column-rename",
    "oldColumnName": "Unlock_Coor_x",
    "newColumnName": "Unlock_Coord_x",
    "description": "Renombra la columna Unlock_Coor_x a Unlock_Coord_x"
  }
]